calamari_ocr/__init__.py
calamari_ocr/version.py
calamari_ocr/ocr/__init__.py
calamari_ocr/ocr/evaluator.py
calamari_ocr/ocr/scenario.py
calamari_ocr/ocr/scenario_params.py
calamari_ocr/ocr/augmentation/__init__.py
calamari_ocr/ocr/augmentation/data_augmenter.py
calamari_ocr/ocr/augmentation/dataaugmentationparams.py
calamari_ocr/ocr/dataset/__init__.py
calamari_ocr/ocr/dataset/codec.py
calamari_ocr/ocr/dataset/data.py
calamari_ocr/ocr/dataset/params.py
calamari_ocr/ocr/dataset/pipeline.py
calamari_ocr/ocr/dataset/datareader/__init__.py
calamari_ocr/ocr/dataset/datareader/base.py
calamari_ocr/ocr/dataset/datareader/extended_prediction.py
calamari_ocr/ocr/dataset/datareader/file.py
calamari_ocr/ocr/dataset/datareader/raw.py
calamari_ocr/ocr/dataset/datareader/abbyy/__init__.py
calamari_ocr/ocr/dataset/datareader/abbyy/reader.py
calamari_ocr/ocr/dataset/datareader/abbyy/xml/__init__.py
calamari_ocr/ocr/dataset/datareader/abbyy/xml/data.py
calamari_ocr/ocr/dataset/datareader/abbyy/xml/exceptions.py
calamari_ocr/ocr/dataset/datareader/abbyy/xml/reader.py
calamari_ocr/ocr/dataset/datareader/abbyy/xml/writer.py
calamari_ocr/ocr/dataset/datareader/generated_line_dataset/__init__.py
calamari_ocr/ocr/dataset/datareader/generated_line_dataset/dataset.py
calamari_ocr/ocr/dataset/datareader/generated_line_dataset/line_generator.py
calamari_ocr/ocr/dataset/datareader/generated_line_dataset/params.py
calamari_ocr/ocr/dataset/datareader/generated_line_dataset/text_generation/__init__.py
calamari_ocr/ocr/dataset/datareader/generated_line_dataset/text_generation/text_generator.py
calamari_ocr/ocr/dataset/datareader/hdf5/__init__.py
calamari_ocr/ocr/dataset/datareader/hdf5/hdf5_dataset_writer.py
calamari_ocr/ocr/dataset/datareader/hdf5/reader.py
calamari_ocr/ocr/dataset/datareader/pagexml/__init__.py
calamari_ocr/ocr/dataset/datareader/pagexml/reader.py
calamari_ocr/ocr/dataset/imageprocessors/__init__.py
calamari_ocr/ocr/dataset/imageprocessors/augmentation.py
calamari_ocr-2.3.1.dist-info/LICENSE
calamari_ocr-2.3.1.dist-info/METADATA
calamari_ocr-2.3.1.dist-info/WHEEL
calamari_ocr-2.3.1.dist-info/entry_points.txt
calamari_ocr-2.3.1.dist-info/top_level.txt
calamari_ocr-2.3.1.dist-info/RECORD
