Metadata-Version: 2.1
Name: calamari_ocr
Version: 2.3.1
Summary: Line based ATR Engine based on OCRopy
Author: Christoph Wick
Author-email: christoph.wick@informatik.uni-wuerzburg.de
License: GPL version 3
Project-URL: homepage, https://github.com/Calamari-OCR/calamari
Keywords: OCR,HTR,optical character recognition
Classifier: Programming Language :: Python :: 3
Classifier: Operating System :: OS Independent
Classifier: License :: OSI Approved :: GNU General Public License v3 (GPLv3)
Classifier: Development Status :: 5 - Production/Stable
Classifier: Environment :: Console
Classifier: Environment :: GPU :: NVIDIA CUDA
Classifier: Intended Audience :: Developers
Classifier: Intended Audience :: Education
Classifier: Intended Audience :: Science/Research
Classifier: Topic :: Scientific/Engineering :: Artificial Intelligence
Classifier: Topic :: Scientific/Engineering :: Image Recognition
Classifier: Topic :: Software Development :: Libraries :: Python Modules
Classifier: Topic :: Text Processing :: General
Requires-Python: >=3.7
License-File: LICENSE
Requires-Dist: edit-distance
Requires-Dist: h5py
Requires-Dist: lxml
Requires-Dist: python-bidi~=0.4.2
Requires-Dist: tensorflow>=2.4.0
Requires-Dist: ocrd-fork-tfaip>=1.2.7
Requires-Dist: xlsxwriter
Requires-Dist: importlib-resources; python_version < "3.10"
Provides-Extra: test
Requires-Dist: pytest; extra == "test"
Requires-Dist: pytest-cov; extra == "test"
Requires-Dist: pytest-isolate; extra == "test"
Requires-Dist: pytest-xdist; extra == "test"
Requires-Dist: flake8; extra == "test"
